LICENSE
README.md
setup.py
metasequoia/__init__.py
metasequoia.egg-info/PKG-INFO
metasequoia.egg-info/SOURCES.txt
metasequoia.egg-info/dependency_links.txt
metasequoia.egg-info/requires.txt
metasequoia.egg-info/top_level.txt
metasequoia/application/__init__.py
metasequoia/application/application.py
metasequoia/application/main_page.py
metasequoia/application/mode.py
metasequoia/core/__init__.py
metasequoia/core/config.py
metasequoia/core/connector.py
metasequoia/core/objects.py
metasequoia/core/plugin.py
metasequoia/plugins/__init__.py
metasequoia/plugins/get_kafka_topic_offset/__init__.py
metasequoia/plugins/get_kafka_topic_offset/plugin_main.py
metasequoia/utils/__init__.py
metasequoia/utils/datax_util.py
metasequoia/utils/datetime_util.py
metasequoia/utils/kafka_util.py
metasequoia/utils/markdown_util.py
metasequoia/utils/mysql_util.py