Metadata-Version: 2.1
Name: metasequoia
Version: 0.1.0
Summary: Metasequoia工具箱
Home-page: https://github.com/ChangxingJiang/metasequoia
Author: changxing
Author-email: 1278729001@qq.com
License: MIT License
Platform: all
Classifier: Intended Audience :: Developers
Classifier: Operating System :: OS Independent
Classifier: Natural Language :: Chinese (Simplified)
Classifier: Programming Language :: Python
Classifier: Programming Language :: Python :: 3
Classifier: Topic :: Software Development :: Libraries
License-File: LICENSE
Requires-Dist: kafka_python>=2.0.2
Requires-Dist: PyMySQL>=1.1.0
Requires-Dist: sshtunnel>=0.4.0
Requires-Dist: streamlit>=1.32.0
Requires-Dist: streamlit_app>=0.0.2
